AUTHORS.md
CHANGELOG.md
CONTRIBUTING.md
LICENSE
MANIFEST.in
README.md
setup.cfg
setup.py
docs/Makefile
docs/conf.py
docs/make.bat
ebr_board/__init__.py
ebr_board/app.py
ebr_board/aws_lambda.py
ebr_board/config.py
ebr_board/models.py
ebr_board.egg-info/PKG-INFO
ebr_board.egg-info/SOURCES.txt
ebr_board.egg-info/dependency_links.txt
ebr_board.egg-info/not-zip-safe
ebr_board.egg-info/requires.txt
ebr_board.egg-info/top_level.txt
ebr_board/api/__init__.py
ebr_board/api/tests.py
ebr_board/api/job/__init__.py
ebr_board/api/job/job.py
ebr_board/api/job/build/__init__.py
ebr_board/api/job/build/build.py
ebr_board/api/job/build/test/__init__.py
ebr_board/api/job/build/test/tests.py
ebr_board/database/__init__.py
ebr_board/database/queries.py
tests/__init__.py
tests/test_aws_lambda.py
tests/test_config.py
tests/test_queries.py