Metadata-Version: 2.1
Name: ebr-board
Version: 0.2.0
Summary: RESTful interface for Elastic Build Results.
Home-page: https://github.com/tomtom-international/ebr-board
Author: Eugene Davis
Author-email: eugene.davis@tomtom.com
License: Apache Software License 2.0
Keywords: ebr_board
Platform: UNKNOWN
Classifier: Development Status :: 2 - Pre-Alpha
Classifier: Intended Audience :: Developers
Classifier: License :: OSI Approved :: Apache Software License
Classifier: Natural Language :: English
Classifier: Programming Language :: Python :: 3
Classifier: Programming Language :: Python :: 3.6
Classifier: Programming Language :: Python :: 3.7
Provides-Extra: aws_lambda
